{
  "user_id": "1646",
  "cart_id": "531364",
  "products": [
    {
      "pattern": "197",
      "eco_collection": "0",
      "tier_prices": [],
      "tsk": 1539030813030,
      "custom_attributes": null,
      "size_options": [
        167,
        168,
        169,
        170,
        171
      ],
      "regular_price": 29.520001,
      "final_price": 29.520001,
      "erin_recommends": "0",
      "price": 24,
      "color_options": [
        49,
        53,
        60
      ],
      "id": 1563,
      "sku": "WS01-XS-Green",
      "image": "/w/s/ws01-green_main.jpg",
      "new": "0",
      "thumbnail": "/w/s/ws01-green_main.jpg",
      "visibility": 4,
      "type_id": "configurable",
      "tax_class_id": "2",
      "climate": "205,209",
      "style_general": "136",
      "url_key": "gwyn-endurance-tee-xs-green",
      "performance_fabric": "0",
      "sale": "0",
      "max_price": 29.520001,
      "minimal_regular_price": 29.520001,
      "required_options": "0",
      "material": "152,38",
      "special_price": 0,
      "minimal_price": 29.520001,
      "name": "Gwyn Endurance Tee",
      "max_regular_price": 29.520001,
      "status": 1,
      "priceTax": 5.5200000000000005,
      "priceInclTax": 29.52,
      "specialPriceTax": null,
      "specialPriceInclTax": null,
      "sgn": "q0v5IK7MiDzrDiWGs592AUDT2FsgTacHODoQucUYOp4",
      "_score": 0,
      "slug": "gwyn-endurance-tee-1577",
      "errors": {},
      "info": {
        "stock": "In stock!"
      },
      "parentSku": "WS01",
      "options": [
        {
          "label": "color",
          "value": "Green"
        },
        {
          "label": "size",
          "value": "XS"
        }
      ],
      "product_option": {
        "extension_attributes": {
          "configurable_item_options": [
            {
              "option_id": "93",
              "option_value": 53
            },
            {
              "option_id": "142",
              "option_value": 167
            }
          ]
        }
      },
      "qty": 1,
      "is_configured": true,
      "color": "53",
      "small_image": "/w/s/ws01-green_main.jpg",
      "has_options": "0",
      "msrp_display_actual_price_type": "0",
      "size": "167",
      "onlineStockCheckid": "1544083446930-34c7201b-faf9-8bbd-fcde-e880dd817463",
      "is_in_stock": true,
      "server_item_id": 64845,
      "server_cart_id": "531364",
      "prev_qty": 1,
      "totals": {
        "item_id": 64845,
        "price": 24,
        "base_price": 24,
        "qty": 1,
        "row_total": 24,
        "base_row_total": 24,
        "row_total_with_discount": 0,
        "tax_amount": 4.69,
        "base_tax_amount": 4.69,
        "tax_percent": 23,
        "discount_amount": 3.6,
        "base_discount_amount": 3.6,
        "discount_percent": 15,
        "price_incl_tax": 29.52,
        "base_price_incl_tax": 29.52,
        "row_total_incl_tax": 29.52,
        "base_row_total_incl_tax": 29.52,
        "options": [
          {
            "value": "Green",
            "label": "Color"
          },
          {
            "value": "XS",
            "label": "Size"
          }
        ],
        "weee_tax_applied_amount": null,
        "weee_tax_applied": null,
        "name": "Gwyn Endurance Tee"
      },
      "stock": {
        "item_id": 1563,
        "product_id": 1563,
        "stock_id": 1,
        "qty": 95,
        "is_in_stock": true,
        "is_qty_decimal": false,
        "show_default_notification_message": false,
        "use_config_min_qty": true,
        "min_qty": 0,
        "use_config_min_sale_qty": 1,
        "min_sale_qty": 1,
        "use_config_max_sale_qty": true,
        "max_sale_qty": 10000,
        "use_config_backorders": true,
        "backorders": 0,
        "use_config_notify_stock_qty": true,
        "notify_stock_qty": 1,
        "use_config_qty_increments": true,
        "qty_increments": 0,
        "use_config_enable_qty_inc": true,
        "enable_qty_increments": false,
        "use_config_manage_stock": true,
        "manage_stock": true,
        "low_stock_date": null,
        "is_decimal_divided": false,
        "stock_status_changed_auto": 0
      }
    }
  ],
  "addressInformation": {
    "shippingAddress": {
      "region": "hhh",
      "region_id": 0,
      "country_id": "LT",
      "street": [
        "UnderTheSea",
        "1"
      ],
      "company": "NA",
      "telephone": "",
      "postcode": "12341",
      "city": "ddddd",
      "firstname": "Zalias",
      "lastname": "Ananasas",
      "email": "avad47@gmail.com",
      "region_code": ""
    },
    "billingAddress": {
      "region": "hhh",
      "region_id": 0,
      "country_id": "LT",
      "street": [
        "UnderTheSea",
        "1"
      ],
      "telephone": "",
      "postcode": "12341",
      "city": "ddddd",
      "firstname": "Zalias",
      "lastname": "Ananasas",
      "email": "avad47@gmail.com",
      "region_code": ""
    },
    "shipping_method_code": "flatrate",
    "shipping_carrier_code": "flatrate",
    "payment_method_code": "cashondelivery",
    "payment_method_additional": {}
  },
  "order_id": "1544083474417-ed9fbb21-a78d-dad1-dc74-8073b05afc21",
  "transmited": true,
  "created_at": "2018-12-06T08:04:34.417Z",
  "updated_at": "2018-12-06T08:04:34.417Z",
  "transmited_at": "2018-12-06T08:04:53.069Z"
}